DESCRIPTION.rst
MANIFEST.in
README.rst
cloud-resolve-conflicts
setup.py
cloud_resolve_conflicts/__init__.py
cloud_resolve_conflicts/cloud_resolve_conflicts.py
cloud_resolve_conflicts.egg-info/PKG-INFO
cloud_resolve_conflicts.egg-info/SOURCES.txt
cloud_resolve_conflicts.egg-info/dependency_links.txt
cloud_resolve_conflicts.egg-info/requires.txt
cloud_resolve_conflicts.egg-info/top_level.txt