Metadata-Version: 1.1
Name: cloud-resolve-conflicts
Version: 0.0.6
Summary: ownCloud and Seafile conflict resolver
Home-page: https://bitbucket.org/rominf/cloud-resolve-conflicts
Author: Roman Inflianskas
Author-email: infroma@gmail.com
License: LGPLv3+
Keywords: cloud seafile owncloud remove conflict file duplicate
Platform: UNKNOWN
Classifier: Development Status :: 3 - Alpha
Classifier: Intended Audience :: End Users/Desktop
Classifier: Environment :: Console
Classifier: Topic :: Utilities
Classifier: License :: OSI Approved :: GNU General Public License v3 or later (GPLv3+)
Classifier: Programming Language :: Python :: 3
Classifier: Programming Language :: Python :: 3.3
Classifier: Programming Language :: Python :: 3.4
